bgphoria/__init__.py
bgphoria/bgpclient.py
bgphoria/connection.py
bgphoria/constants.py
bgphoria/exceptions.py
bgphoria/main.py
bgphoria/messages.py
bgphoria/metadata.py
bgphoria-0.0.0.dist-info/LICENSE
bgphoria-0.0.0.dist-info/METADATA
bgphoria-0.0.0.dist-info/WHEEL
bgphoria-0.0.0.dist-info/top_level.txt
bgphoria-0.0.0.dist-info/RECORD
