Metadata-Version: 2.2
Name: bgphoria
Version: 0.0.0
Summary: Simple Python BGP implementation
Home-page: https://github.com/interstellio/bgphoria
Author: Interstellio IO (PTY) LTD
Author-email: "Interstellio IO (PTY) LTD" <opensource@interstellio.io>
Maintainer: Interstellio IO (PTY) LTD
Maintainer-email: opensource@interstellio.io
Project-URL: Homepage, https://github.com/interstellio/bgphoria
Project-URL: Documentation, https://bgphoria.readthedocs.io
Requires-Python: >=3.10
License-File: LICENSE
Dynamic: author
Dynamic: home-page
Dynamic: maintainer
Dynamic: maintainer-email
Dynamic: requires-python
